{
    "welcome": "Welcome to Pong!",
    "play": "Play",
    "tournament": "Tournament",
    "chatendirect": "Live Chat",
    "JouerauPong": "Play Pong",
    "Lancerunepartie": "Start a Game",
    "Classement": "Ranking",
    "Ouvrir": "Open",
    "Top10": "Top 10",
    "Home": "Home",
    "Chat": "Chat",
    "Profile": "Profile",
    "Login": "Login",
    "Utilisateursconnectes": "Connected Users",
    "Global": "Global",
    "Serveur": "Server",
    "Bienvenuedanslechat": "Welcome to the chat!",
    "Votremessage": "Your message",
    "Envoyer": "Send",
    "Email": "Email",
    "Jen_aipasdecompte_jeveuxm_inscrire": "I don't have an account, I want to register",
    "Motdepasse": "Password"
}
